mmorpg_scraper/__init__.py
mmorpg_scraper/app.py
mmorpg_scraper/scraper/__init__.py
mmorpg_scraper/scraper/constants.py
mmorpg_scraper/scraper/exceptions.py
mmorpg_scraper/scraper/game_detail.py
mmorpg_scraper/scraper/game_list.py
mmorpg_scraper/scraper/headers_generator.py
mmorpg_scraper/scraper/request.py
mmorpg_scraper/scraper/scraper.py
tests/__init__.py
tests/test.py
mmorpg_scraper-0.0.3.dist-info/LICENSE
mmorpg_scraper-0.0.3.dist-info/METADATA
mmorpg_scraper-0.0.3.dist-info/WHEEL
mmorpg_scraper-0.0.3.dist-info/top_level.txt
mmorpg_scraper-0.0.3.dist-info/RECORD
