Metadata-Version: 2.1
Name: mmorpg-scraper
Version: 0.0.3
Summary: Web scraper
Home-page: https://github.com/canberkeh/mmorpg-scraper
Author: Can Berke Horozal
Author-email: canberkehorozal@gmail.com
License: UNKNOWN
Platform: UNKNOWN
Classifier: Programming Language :: Python :: 3
Classifier: License :: OSI Approved :: MIT License
Classifier: Operating System :: OS Independent
Requires-Python: >=3.7
License-File: LICENSE
Requires-Dist: beautifulsoup4 (>=4.10.0)
Requires-Dist: requests (>=2.23.0)
